livekit/plugins/avatarioai/__init__.py
livekit/plugins/avatarioai/api.py
livekit/plugins/avatarioai/avatar.py
livekit/plugins/avatarioai/log.py
livekit/plugins/avatarioai/version.py
livekit_plugins_avatarioai-1.0.22.dist-info/METADATA
livekit_plugins_avatarioai-1.0.22.dist-info/WHEEL
livekit_plugins_avatarioai-1.0.22.dist-info/RECORD
